taxii_services/__init__.py
taxii_services/admin.py
taxii_services/exceptions.py
taxii_services/management.py
taxii_services/middleware.py
taxii_services/models.py
taxii_services/urls.py
taxii_services/version.py
taxii_services/views.py
taxii_services/handlers/__init__.py
taxii_services/message_handlers/__init__.py
taxii_services/message_handlers/base_handlers.py
taxii_services/message_handlers/collection_information_request_handlers.py
taxii_services/message_handlers/discovery_request_handlers.py
taxii_services/message_handlers/inbox_message_handlers.py
taxii_services/message_handlers/poll_fulifllment_request_handlers.py
taxii_services/message_handlers/poll_request_handlers.py
taxii_services/message_handlers/subscription_request_handlers.py
taxii_services/query_handlers/__init__.py
taxii_services/query_handlers/base_handlers.py
taxii_services/query_handlers/stix_xml_111_handler.py
taxii_services/util/__init__.py
taxii_services/util/request_utils.py
tests/__init__.py
tests/base.py
tests/constants.py
tests/helpers.py
tests/test_basics.py
tests/test_collection_information.py
tests/test_discovery.py
tests/test_inbox_message.py
tests/test_models.py
tests/test_poll_fulfillment.py
tests/test_poll_request.py
tests/test_protocol.py
tests/test_query_handler.py
tests/test_settings.py
tests/test_subscription.py
taxii_services-0.6.dist-info/LICENSE.txt
taxii_services-0.6.dist-info/METADATA
taxii_services-0.6.dist-info/WHEEL
taxii_services-0.6.dist-info/top_level.txt
taxii_services-0.6.dist-info/RECORD
