Metadata-Version: 2.1
Name: taxii-services
Version: 0.6
Summary: Django TAXII installable app & utilities for creating TAXII Django Web Apps.
Home-page: http://taxii.mitre.org/
Author: Mark Davidson
Author-email: mdavidson@mitre.org
License: UNKNOWN
Keywords: taxii django taxii_services django-taxii-services
Platform: UNKNOWN
Classifier: Development Status :: 4 - Beta
Classifier: Intended Audience :: Developers
Classifier: Topic :: Security
Classifier: License :: OSI Approved :: BSD License
Classifier: Programming Language :: Python :: 2
Classifier: Programming Language :: Python :: 2.7
Requires-Dist: Django (>=1.11.19)
Requires-Dist: libtaxii (>=1.1.105)
Requires-Dist: lxml (>=2.2.3)
Requires-Dist: python-dateutil (>=1.4.1)
Provides-Extra: docs
Requires-Dist: Sphinx (==1.3.1) ; extra == 'docs'
Requires-Dist: sphinx-rtd-theme (==0.1.8) ; extra == 'docs'
Provides-Extra: test
Requires-Dist: tox (==1.6.1) ; extra == 'test'
